odoo/addons/redner/README.rst
odoo/addons/redner/__init__.py
odoo/addons/redner/__manifest__.py
odoo/addons/redner/converter.py
odoo/addons/redner/hooks.py
odoo/addons/redner/redner.py
odoo/addons/redner/.badges/code_style-ruff.svg
odoo/addons/redner/.badges/coverage.svg
odoo/addons/redner/.badges/licence-AGPL--3-blue.svg
odoo/addons/redner/.badges/maturity.svg
odoo/addons/redner/.badges/pylint.svg
odoo/addons/redner/controllers/__init__.py
odoo/addons/redner/controllers/main.py
odoo/addons/redner/i18n/fr.po
odoo/addons/redner/models/__init__.py
odoo/addons/redner/models/ir_actions_report.py
odoo/addons/redner/models/mail_template.py
odoo/addons/redner/models/redner_report.py
odoo/addons/redner/models/redner_substitution.py
odoo/addons/redner/models/redner_template.py
odoo/addons/redner/models/res_config_settings.py
odoo/addons/redner/models/substitution_mixin.py
odoo/addons/redner/security/ir.model.access.csv
odoo/addons/redner/static/description/icon.png
odoo/addons/redner/static/description/logo.png
odoo/addons/redner/static/description/thumbnail.png
odoo/addons/redner/static/src/components/dynamic_placeholder_char_field/dynamic_placeholder_char_field.esm.js
odoo/addons/redner/static/src/components/dynamic_placeholder_char_field/dynamic_placeholder_char_field.xml
odoo/addons/redner/static/src/js/redner_report_action.esm.js
odoo/addons/redner/tests/__init__.py
odoo/addons/redner/tests/common.py
odoo/addons/redner/tests/test_ir_actions_report.py
odoo/addons/redner/tests/test_mail_template.py
odoo/addons/redner/tests/test_mimetype.py
odoo/addons/redner/tests/test_redner_template.py
odoo/addons/redner/tests/test_sorting.py
odoo/addons/redner/tests/test_substitution.py
odoo/addons/redner/utils/__init__.py
odoo/addons/redner/utils/formats.py
odoo/addons/redner/utils/mimetype.py
odoo/addons/redner/utils/sorting.py
odoo/addons/redner/views/ir_actions_report.xml
odoo/addons/redner/views/mail_template.xml
odoo/addons/redner/views/menu.xml
odoo_addon_redner-19.0.1.0.1.dist-info/METADATA
odoo_addon_redner-19.0.1.0.1.dist-info/WHEEL
odoo_addon_redner-19.0.1.0.1.dist-info/licenses/LICENSE
odoo_addon_redner-19.0.1.0.1.dist-info/RECORD
