Metadata-Version: 2.4
Name: odoo-addon-redner
Version: 19.0.1.0.1
Summary: Odoo addon to use redner (producer of reports and emails)
Project-URL: changelog, https://orus.io/xcg/odoo-modules/redner/-/blob/branch/19.0/NEWS.rst
Project-URL: documentation, https://xcg.pages.orus.io/odoo-modules/redner/en/
Project-URL: homepage, https://orbeet.io/services/generateur-documents-redner/
Project-URL: repository, https://orus.io/xcg/odoo-modules/redner
Author: XCG SAS
License-Expression: AGPL-3.0-or-later
License-File: LICENSE
Keywords: odoo
Classifier: Development Status :: 5 - Production/Stable
Classifier: Framework :: Odoo
Classifier: Framework :: Odoo :: 19.0
Classifier: Programming Language :: Python
Classifier: Programming Language :: Python :: 3
Classifier: Programming Language :: Python :: 3.10
Classifier: Programming Language :: Python :: 3.11
Classifier: Programming Language :: Python :: 3.12
Classifier: Programming Language :: Python :: 3.13
Requires-Python: >=3.10
Requires-Dist: odoo-addon-converter<19.0.2,>=19.0.1.0.0
Requires-Dist: odoo==19.0.*
Provides-Extra: doc
Requires-Dist: sphinx; extra == 'doc'
Provides-Extra: test
Provides-Extra: unixsocket
Requires-Dist: requests-unixsocket; extra == 'unixsocket'
